nagausspy/__init__.py
nagausspy/_com.py
nagausspy/_commandline.py
nagausspy/analysis.py
nagausspy/frequency.py
nagausspy/geometry.py
nagausspy/nmr.py
nagausspy/reader.py
nagausspy/templates.py
nagausspy/widening_functions.py
nagausspy-0.2.dist-info/LICENSE
nagausspy-0.2.dist-info/METADATA
nagausspy-0.2.dist-info/WHEEL
nagausspy-0.2.dist-info/top_level.txt
nagausspy-0.2.dist-info/RECORD
