Metadata-Version: 2.1
Name: nagausspy
Version: 0.2
Summary: Tools for reading and analyzing Gaussian output files
Author-email: Hadrián Montes Campos <hadrian.montes@usc.es>
Classifier: Programming Language :: Python :: 3
Classifier: Operating System :: OS Independent
Requires-Python: >=3.8
License-File: LICENSE
Requires-Dist: numpy
Requires-Dist: scipy
Requires-Dist: gaddlemaps
Requires-Dist: matplotlib
Requires-Dist: networkx
Requires-Dist: MDanalysis
